operatorio/__init__.py
operatorio/main.py
operatorio-0.2.8.dist-info/METADATA
operatorio-0.2.8.dist-info/WHEEL
operatorio-0.2.8.dist-info/top_level.txt
operatorio-0.2.8.dist-info/RECORD
