Metadata-Version: 2.1
Name: operatorio
Version: 0.2.8
Summary: A Python SDK for the Operator Search API.
Home-page: https://github.com/operatorlabs/sdk/python
Author: David Shi
Author-email: david@operator.io
Classifier: Programming Language :: Python :: 3
Classifier: License :: OSI Approved :: MIT License
Requires-Python: >=3.6
Requires-Dist: requests
